MANIFEST.in
README.md
setup.py
pydfs_lineup_optimizer/__init__.py
pydfs_lineup_optimizer/constants.py
pydfs_lineup_optimizer/context.py
pydfs_lineup_optimizer/exceptions.py
pydfs_lineup_optimizer/exposure_strategy.py
pydfs_lineup_optimizer/fantasy_points_strategy.py
pydfs_lineup_optimizer/lineup.py
pydfs_lineup_optimizer/lineup_exporter.py
pydfs_lineup_optimizer/lineup_importer.py
pydfs_lineup_optimizer/lineup_optimizer.py
pydfs_lineup_optimizer/lineup_printer.py
pydfs_lineup_optimizer/player.py
pydfs_lineup_optimizer/player_pool.py
pydfs_lineup_optimizer/rules.py
pydfs_lineup_optimizer/settings.py
pydfs_lineup_optimizer/stacks.py
pydfs_lineup_optimizer/statistics.py
pydfs_lineup_optimizer/tz.py
pydfs_lineup_optimizer/utils.py
pydfs_lineup_optimizer/version.py
pydfs_lineup_optimizer.egg-info/PKG-INFO
pydfs_lineup_optimizer.egg-info/SOURCES.txt
pydfs_lineup_optimizer.egg-info/dependency_links.txt
pydfs_lineup_optimizer.egg-info/requires.txt
pydfs_lineup_optimizer.egg-info/top_level.txt
pydfs_lineup_optimizer/sites/__init__.py
pydfs_lineup_optimizer/sites/sites_registry.py
pydfs_lineup_optimizer/sites/draftkings/__init__.py
pydfs_lineup_optimizer/sites/draftkings/captain_mode/__init__.py
pydfs_lineup_optimizer/sites/draftkings/captain_mode/importer.py
pydfs_lineup_optimizer/sites/draftkings/captain_mode/settings.py
pydfs_lineup_optimizer/sites/draftkings/classic/__init__.py
pydfs_lineup_optimizer/sites/draftkings/classic/importer.py
pydfs_lineup_optimizer/sites/draftkings/classic/settings.py
pydfs_lineup_optimizer/sites/draftkings/tiers/__init__.py
pydfs_lineup_optimizer/sites/draftkings/tiers/importer.py
pydfs_lineup_optimizer/sites/draftkings/tiers/settings.py
pydfs_lineup_optimizer/sites/fanball/__init__.py
pydfs_lineup_optimizer/sites/fanball/settings.py
pydfs_lineup_optimizer/sites/fanduel/__init__.py
pydfs_lineup_optimizer/sites/fanduel/classic/__init__.py
pydfs_lineup_optimizer/sites/fanduel/classic/importer.py
pydfs_lineup_optimizer/sites/fanduel/classic/settings.py
pydfs_lineup_optimizer/sites/fanduel/single_game/__init__.py
pydfs_lineup_optimizer/sites/fanduel/single_game/importer.py
pydfs_lineup_optimizer/sites/fanduel/single_game/settings.py
