Metadata-Version: 2.1
Name: pydfs-lineup-optimizer
Version: 3.6.0
Summary: Tool for creating optimal lineups for daily fantasy sports
Home-page: https://github.com/DimaKudosh/pydfs-lineup-optimizer
Author: Dima Kudosh
Author-email: dimakudosh@gmail.com
License: MIT
Keywords: dfs,fantasy,sport,lineup,optimize,optimizer,nba,nfl,nhl,mlb
Platform: UNKNOWN
Classifier: Development Status :: 4 - Beta
Classifier: Environment :: Console
Classifier: Intended Audience :: End Users/Desktop
Classifier: Intended Audience :: Developers
Classifier: Operating System :: POSIX
Classifier: Programming Language :: Python
